clinbin/__init__.py
clinbin/anthropometry.py
clinbin/blood.py
clinbin/ehr.py
clinbin/assets/Wei_2024_multimorbidity_weighted_index.json
clinbin-0.2.1.dist-info/METADATA
clinbin-0.2.1.dist-info/WHEEL
clinbin-0.2.1.dist-info/licenses/LICENSE
clinbin-0.2.1.dist-info/RECORD
