Metadata-Version: 2.4
Name: clinbin
Version: 0.2.1
Summary: Use cut-off points from medical guidelines to classify clinical variables.
Project-URL: Homepage, https://gitlab.com/hylkedonker/clinbin
Project-URL: Repository, https://gitlab.com/hylkedonker/clinbin.git
Project-URL: Bug Tracker, https://gitlab.com/hylkedonker/clinbin/-/issues
Author-email: "H. C. Donker" <h.c.donker@umcg.nl>
License-Expression: MIT
License-File: LICENSE
Requires-Python: >=3.12
Requires-Dist: pandas>=2.0.0
